api_gateway/__init__.py
api_gateway/dependencies.py
api_gateway/webapp.py
api_gateway/config/ci.toml
api_gateway/config/defaults.toml
api_gateway/config/prod.toml
api_gateway/config/test.toml
api_gateway/logging/__init__.py
api_gateway/logging/metrics_client.py
api_gateway/logging/models.py
api_gateway/models/__init__.py
api_gateway/models/tool_models.py
api_gateway/services/__init__.py
api_gateway/services/gandalf_helper.py
api_gateway/services/gateway_service.py
api_gateway/services/tool_invoker.py
api_gateway/tool_registry/__init__.py
api_gateway/tool_registry/register_tool.py
api_gateway/tool_registry/tool_registry_controller.py
api_gateway/tool_registry/tool_registry_operations.py
api_gateway/tool_registry/tool_managers/__init__.py
api_gateway/tool_registry/tool_managers/configbin.py
api_gateway/tool_registry/tool_managers/danswer.py
api_gateway/tool_registry/utils/__init__.py
api_gateway/tool_registry/utils/discovery.py
api_gateway/tool_registry/utils/ncp_project_connection.py
api_gateway/tool_registry/utils/validators.py
ncp_tool_registry_cli-0.2.3.dist-info/METADATA
ncp_tool_registry_cli-0.2.3.dist-info/WHEEL
ncp_tool_registry_cli-0.2.3.dist-info/entry_points.txt
ncp_tool_registry_cli-0.2.3.dist-info/RECORD
