Metadata-Version: 2.4
Name: ncp-tool-registry-cli
Version: 0.2.3
Summary: Tool registry CLI
Author-email: Felipe Assumpcao <fassumpcao@netflix.com>
Requires-Python: >=3.7
Requires-Dist: click
Requires-Dist: colorama
Requires-Dist: configbin
Requires-Dist: fastapi
Requires-Dist: jsonpath-ng
Requires-Dist: jsonref
Requires-Dist: metatron
Requires-Dist: nflx-security-util>=0.6.0
Requires-Dist: nflxconfig
Requires-Dist: nflxlog
Requires-Dist: pydantic
Requires-Dist: requests
Requires-Dist: rich
